<T3DataStructure>
  <meta type="array">
    <langDisable>1</langDisable>
  </meta>
  <sheets>
    <!-- Sheet: Settings -->
    <sDEF>
      <ROOT>
        <TCEforms>
          <sheetTitle>Einstellungen</sheetTitle>
        </TCEforms>
        <type>array</type>
        <el>
          <settings.locationFilter.locations>
            <TCEforms>
              <label>Veranstaltungsort</label>
              <config>
                <type>select</type>
                <itemsProcFunc>Priorist\EdmTypo3\Backend\ItemsProcFunc->getLocations</itemsProcFunc>
                <renderType>selectMultipleSideBySide</renderType>
                <items>
                  <!-- empty by default -->
                </items>
                <minitems>1</minitems>
              </config>
            </TCEforms>
          </settings.locationFilter.locations>
        </el>
      </ROOT>
    </sDEF>
  </sheets>
</T3DataStructure>
